[
  {
    "question": "はじく",
    "meaning": "1. Không thấm ( nước...)2. Không chấp nhận những thứ không đủ điều kiện",
    "furigana": ""
  },
  {
    "question": "しくじる",
    "meaning": "1. Thất bại 2. Bị cách chức, bị sa thải",
    "furigana": ""
  },
  {
    "question": "渋る",
    "meaning": "しぶる Chần chừ, lưỡng lự",
    "furigana": ""
  },
  {
    "question": "嵩張る",
    "meaning": "かさばる Cồng kềnh",
    "furigana": ""
  },
  {
    "question": "滲む",
    "meaning": "にじむ 1. Bị nhoè, bị loang, bị lan rộng ( chất lỏng)2. Toát ra",
    "furigana": ""
  },
  {
    "question": "ばてる",
    "meaning": "Phờ phạc, mệt mỏi, uể oải",
    "furigana": ""
  },
  {
    "question": "交える",
    "meaning": "まじえる 1. Đan xen, xen lẫn2. Kết hợp, trao đổi",
    "furigana": ""
  },
  {
    "question": "危ぶむ",
    "meaning": "あやぶむ Lo rằng, e rằng sẽ không",
    "furigana": ""
  },
  {
    "question": "覆る",
    "meaning": "くつがえる 1. Lật ngược 2. Lật lại, xem lại",
    "furigana": ""
  },
  {
    "question": "挫ける",
    "meaning": "くじける Nản chí",
    "furigana": ""
  },
  {
    "question": "貫く",
    "meaning": "つらぬく Xuyên qua, xuyên suốt",
    "furigana": ""
  },
  {
    "question": "ぼやく",
    "meaning": "Càm ràm, càu nhàu, than phiền",
    "furigana": ""
  },
  {
    "question": "施す",
    "meaning": "ほどこす 1. Thi hành, thực hiện2. Từ thiệu, giúp đỡ3. Đính thêm, gắn thêm ( trang trí)",
    "furigana": ""
  },
  {
    "question": "懐く",
    "meaning": "なつく Quấn quýt, gần gũi, bám lấy",
    "furigana": ""
  },
  {
    "question": "費やす",
    "meaning": "ついやす Tiêu hao, tiêu tốn",
    "furigana": ""
  },
  {
    "question": "掲げる",
    "meaning": "かかげる 1. Gương lên, treo lên2. Nêu lên",
    "furigana": ""
  },
  {
    "question": "跳ねる",
    "meaning": "はねる Nhảy lên, bắn lên, văng lên",
    "furigana": ""
  },
  {
    "question": "挙げる",
    "meaning": "あげる 1. Giơ lên, đưa lên2. Nêu ra, đưa ra, đề cử3. Dốc hết4. Tổ chức nghi lễ, nghi thức ( trước nhiều người)",
    "furigana": ""
  },
  {
    "question": "安らぐ",
    "meaning": "やすらぐ Yên tâm, thư thái, thanh thản",
    "furigana": ""
  },
  {
    "question": "培う",
    "meaning": "つちかう Bồi dưỡng, vun đắp, trau dồi",
    "furigana": ""
  },
  {
    "question": "遠ざける",
    "meaning": "とおざける Xua đi, tránh khỏi, lạnh nhạt ( tình cảm)",
    "furigana": ""
  },
  {
    "question": "案じる",
    "meaning": "あんじる Lo lắng, băn khoăn",
    "furigana": ""
  },
  {
    "question": "よける",
    "meaning": "Né, tránh ( khỏi)",
    "furigana": ""
  },
  {
    "question": "歩む",
    "meaning": "あゆむ 1. Bước đi 2. Tiến lên, bước đi, trải qua ( nghĩa trừu tượng)",
    "furigana": ""
  },
  {
    "question": "なぞる",
    "meaning": "1. Tô theo, vẽ theo ( mẫu có sẵn)2. Bắt chước lại",
    "furigana": ""
  },
  {
    "question": "伝う",
    "meaning": "つたう Đi theo, lần theo, di chuyển theo",
    "furigana": ""
  },
  {
    "question": "浮かれる",
    "meaning": "うかれる Vui vẻ, hưng phấn, lâng lâng",
    "furigana": ""
  },
  {
    "question": "極める",
    "meaning": "きわめる 1. Cực kỳ, vô cùng 2. Chinh phục",
    "furigana": ""
  },
  {
    "question": "潤う",
    "meaning": "うるおう 1. Ẩm ướt 2. Cảm động và thoải mái, mãn nguyện3. Có lợi ( về kinh tế)",
    "furigana": ""
  },
  {
    "question": "遡る",
    "meaning": "さかのぼる 1. Đi ngược dòng2. Quay về quá khứ, cội nguồn",
    "furigana": ""
  },
  {
    "question": "仰ぐ",
    "meaning": "あおぐ 1. Ngước lên 2. Ngưỡng mộ, tôn kính3. Thỉnh giáo, hỏi ý kiến",
    "furigana": ""
  },
  {
    "question": "もてなす",
    "meaning": "Tiếp đãi, tiếp đón",
    "furigana": ""
  },
  {
    "question": "反らす",
    "meaning": "そらす uốn cong, ưỡn",
    "furigana": ""
  },
  {
    "question": "拒む",
    "meaning": "こばむ Từ chối, khước từ",
    "furigana": ""
  },
  {
    "question": "委ねる",
    "meaning": "ゆだねる 1. Giao phó2. Dựa vào",
    "furigana": ""
  },
  {
    "question": "歪む",
    "meaning": "ゆがむ 1. Biến dạng2. Sai lệch, méo mó2. Lệch lạc ( suy nghĩ, hành động)",
    "furigana": ""
  },
  {
    "question": "装う",
    "meaning": "よそおう 1. Làm đẹp, trang trí2. Giả vờ",
    "furigana": ""
  },
  {
    "question": "据える",
    "meaning": "すえる Đặt, để, cố định",
    "furigana": ""
  },
  {
    "question": "志す",
    "meaning": "こころざす Quyết chí làm, theo đuổi",
    "furigana": ""
  },
  {
    "question": "誇る",
    "meaning": "ほこる Tự hào",
    "furigana": ""
  },
  {
    "question": "漏れる",
    "meaning": "もれる 1. Rò rỉ, lọt ra ngoài, để lộ2. bị sót, bị lọt, bị thiếu",
    "furigana": ""
  },
  {
    "question": "響く",
    "meaning": "ひびく 1. Vang lên, vọng lại 2. Chạm đến ( trái tim)3. Ảnh hưởng",
    "furigana": ""
  },
  {
    "question": "励ます",
    "meaning": "はげます Động viên, khích lệ",
    "furigana": ""
  },
  {
    "question": "こじれる",
    "meaning": "Xấu đi, trở lên rối ren, phức tạp",
    "furigana": ""
  },
  {
    "question": "競う",
    "meaning": "Cạnh tranh, thi đấu",
    "furigana": ""
  },
  {
    "question": "老ける",
    "meaning": "ふける (Trông, nhìn) Già đi, lão hoá",
    "furigana": ""
  },
  {
    "question": "おだてる",
    "meaning": "Ninh nọt, tâng bốc",
    "furigana": ""
  },
  {
    "question": "促す",
    "meaning": "うながす 1. Thúc giục, hối thúc2. Thúc đẩy3. Kêu gọi, khuyến khích, lưu ý, nhắc nhở",
    "furigana": ""
  },
  {
    "question": "もがく",
    "meaning": "Vật lộn, đấu tranh, vùng vãy",
    "furigana": ""
  },
  {
    "question": "粘る",
    "meaning": "ねばる 1. Dính, dai2. Kiên trì, bền bỉ3. Đeo bám , nhây",
    "furigana": ""
  }
]